ecss_chat_client/__init__.py
ecss_chat_client/const.py
ecss_chat_client/scheme.py
ecss_chat_client/services/__init__.py
ecss_chat_client/services/auth.py
ecss_chat_client/services/avatar.py
ecss_chat_client/services/basic_websocket_client.py
ecss_chat_client/services/bots.py
ecss_chat_client/services/config.py
ecss_chat_client/services/directs.py
ecss_chat_client/services/folders.py
ecss_chat_client/services/groups.py
ecss_chat_client/services/info.py
ecss_chat_client/services/lib.py
ecss_chat_client/services/messages.py
ecss_chat_client/services/polls.py
ecss_chat_client/services/preferences.py
ecss_chat_client/services/rooms.py
ecss_chat_client/services/server.py
ecss_chat_client/services/spotlight.py
ecss_chat_client/services/supergroups.py
ecss_chat_client/services/test_websocket_client.py
ecss_chat_client/services/testing.py
ecss_chat_client/services/threads.py
ecss_chat_client/services/tus.py
ecss_chat_client/services/users.py
ecss_chat_client/types/__init__.py
ecss_chat_client/types/attachments.py
ecss_chat_client/types/folders.py
ecss_chat_client/types/rooms.py
ecss_chat_client/types/settings.py
ecss_chat_client/types/spotlight.py
ecss_chat_client/utils/__init__.py
ecss_chat_client/utils/decorators.py
ecss_chat_client-1.5.49.dist-info/licenses/LICENSE
ecss_chat_client-1.5.49.dist-info/METADATA
ecss_chat_client-1.5.49.dist-info/WHEEL
ecss_chat_client-1.5.49.dist-info/top_level.txt
ecss_chat_client-1.5.49.dist-info/RECORD
